splurge_test_namer/__init__.py
splurge_test_namer/__main__.py
splurge_test_namer/cli.py
splurge_test_namer/exceptions.py
splurge_test_namer/namer.py
splurge_test_namer/parser.py
splurge_test_namer/util_helpers.py
splurge_test_namer-2025.1.0.dist-info/licenses/LICENSE
splurge_test_namer-2025.1.0.dist-info/METADATA
splurge_test_namer-2025.1.0.dist-info/WHEEL
splurge_test_namer-2025.1.0.dist-info/entry_points.txt
splurge_test_namer-2025.1.0.dist-info/top_level.txt
splurge_test_namer-2025.1.0.dist-info/RECORD
