Metadata-Version: 2.4
Name: splurge-test-namer
Version: 2025.1.0
Summary: Rename test modules based on sentinel metadata and optional import-following logic
Author: Jim Schilling
License-Expression: MIT
Project-URL: homepage, https://github.com/jim-schilling/splurge-test-namer
Keywords: tests,rename,sentinel,naming
Classifier: Development Status :: 4 - Beta
Classifier: Programming Language :: Python :: 3
Classifier: Programming Language :: Python :: 3.10
Classifier: Programming Language :: Python :: 3.11
Classifier: Programming Language :: Python :: 3.12
Classifier: Programming Language :: Python :: 3.13
Requires-Python: >=3.10
License-File: LICENSE
Provides-Extra: dev
Requires-Dist: pytest>=7.0; extra == "dev"
Requires-Dist: pytest-cov; extra == "dev"
Requires-Dist: pytest-mock; extra == "dev"
Requires-Dist: pre-commit; extra == "dev"
Requires-Dist: ruff; extra == "dev"
Dynamic: license-file
